{
  "layer": "quakes",
  "updated": "2026-07-22T20:30:46Z",
  "count": 202,
  "points": [
    {
      "id": "nc75403892",
      "lon": -122.55249786377,
      "lat": 37.7651672363281,
      "depth": 11.7399997711182,
      "mag": 1.46,
      "place": "6 km NW of San Francisco Zoo, CA",
      "time": 1784751976870,
      "url": "https://earthquake.usgs.gov/earthquakes/eventpage/nc75403892"
    },
    {
      "id": "aka2026okqwer",
      "lon": -151.564,
      "lat": 60.139,
      "depth": 57.9,
      "mag": 2.6,
      "place": "11 km NNE of Ninilchik, Alaska",
      "time": 1784751155636,
      "url": "https://earthquake.usgs.gov/earthquakes/eventpage/aka2026okqwer"
    },
    {
      "id": "hv75006522",
      "lon": -155.445831298828,
      "lat": 19.117166519165,
      "depth": 24.5400009155273,
      "mag": 1.72,
      "place": "10 km SSE of Pāhala, Hawaii",
      "time": 1784750617520,
      "url": "https://earthquake.usgs.gov/earthquakes/eventpage/hv75006522"
    },
    {
      "id": "ci40659474",
      "lon": -117.9515,
      "lat": 35.9568333333333,
      "depth": 3.75,
      "mag": 0.53,
      "place": "5 km WNW of Little Lake, CA",
      "time": 1784749958770,
      "url": "https://earthquake.usgs.gov/earthquakes/eventpage/ci40659474"
    },
    {
      "id": "aka2026okqcho",
      "lon": -150.843,
      "lat": 61.525,
      "depth": 64.6,
      "mag": 1.8,
      "place": "17 km W of Susitna, Alaska",
      "time": 1784749779323,
      "url": "https://earthquake.usgs.gov/earthquakes/eventpage/aka2026okqcho"
    },
    {
      "id": "nc75403877",
      "lon": -122.795333862305,
      "lat": 38.8211669921875,
      "depth": 2.51999998092651,
      "mag": 1.03,
      "place": "6 km NW of The Geysers, CA",
      "time": 1784749582000,
      "url": "https://earthquake.usgs.gov/earthquakes/eventpage/nc75403877"
    },
    {
      "id": "ci40659458",
      "lon": -117.486666666667,
      "lat": 33.868,
      "depth": -0.45,
      "mag": 1.21,
      "place": "3 km ESE of Home Gardens, CA",
      "time": 1784748632750,
      "url": "https://earthquake.usgs.gov/earthquakes/eventpage/ci40659458"
    },
    {
      "id": "hv75006507",
      "lon": -155.369659423828,
      "lat": 19.1229991912842,
      "depth": 27.8400001525879,
      "mag": 1.83,
      "place": "14 km SE of Pāhala, Hawaii",
      "time": 1784748189750,
      "url": "https://earthquake.usgs.gov/earthquakes/eventpage/hv75006507"
    },
    {
      "id": "tx2026oihbmw",
      "lon": -103.892,
      "lat": 31.949,
      "depth": 4.7008,
      "mag": 1.6,
      "place": "34 km SSE of Malaga, New Mexico",
      "time": 1784747877193,
      "url": "https://earthquake.usgs.gov/earthquakes/eventpage/tx2026oihbmw"
    },
    {
      "id": "nc75403857",
      "lon": -121.212333679199,
      "lat": 36.6043319702148,
      "depth": 3.8199999332428,
      "mag": 1.98,
      "place": "10 km NW of Pinnacles, CA",
      "time": 1784746432330,
      "url": "https://earthquake.usgs.gov/earthquakes/eventpage/nc75403857"
    },
    {
      "id": "aka2026okoeco",
      "lon": -153.322,
      "lat": 56.127,
      "depth": 6.1,
      "mag": 3.2,
      "place": "105 km SSE of Akhiok, Alaska",
      "time": 1784746291884,
      "url": "https://earthquake.usgs.gov/earthquakes/eventpage/aka2026okoeco"
    },
    {
      "id": "aka2026okobqy",
      "lon": -153.374,
      "lat": 56.153,
      "depth": 5.2,
      "mag": 2.8,
      "place": "100 km SSE of Akhiok, Alaska",
      "time": 1784746119662,
      "url": "https://earthquake.usgs.gov/earthquakes/eventpage/aka2026okobqy"
    },
    {
      "id": "us7000t2hm",
      "lon": 179.9243,
      "lat": -31.5416,
      "depth": 346.444,
      "mag": 4.8,
      "place": "Kermadec Islands region",
      "time": 1784744979600,
      "url": "https://earthquake.usgs.gov/earthquakes/eventpage/us7000t2hm"
    },
    {
      "id": "tx2026oieytt",
      "lon": -104.251,
      "lat": 31.654,
      "depth": 6.5613,
      "mag": 1.7,
      "place": "57 km NW of Toyah, Texas",
      "time": 1784744081530,
      "url": "https://earthquake.usgs.gov/earthquakes/eventpage/tx2026oieytt"
    },
    {
      "id": "aka2026okmwzn",
      "lon": -153.375,
      "lat": 56.199,
      "depth": 16.2,
      "mag": 4.9,
      "place": "96 km SSE of Akhiok, Alaska",
      "time": 1784744003544,
      "url": "https://earthquake.usgs.gov/earthquakes/eventpage/aka2026okmwzn"
    },
    {
      "id": "hv75006462",
      "lon": -155.388671875,
      "lat": 18.9598331451416,
      "depth": 31.1800003051758,
      "mag": 1.74,
      "place": "23 km ESE of Naalehu, Hawaii",
      "time": 1784743662590,
      "url": "https://earthquake.usgs.gov/earthquakes/eventpage/hv75006462"
    },
    {
      "id": "aka2026okmplz",
      "lon": -154.147,
      "lat": 59.674,
      "depth": 166,
      "mag": 2,
      "place": "12 km S of Pedro Bay, Alaska",
      "time": 1784743493657,
      "url": "https://earthquake.usgs.gov/earthquakes/eventpage/aka2026okmplz"
    },
    {
      "id": "ci40659402",
      "lon": -117.951166666667,
      "lat": 35.9561666666667,
      "depth": 2.75,
      "mag": 0.69,
      "place": "5 km WNW of Little Lake, CA",
      "time": 1784743447200,
      "url": "https://earthquake.usgs.gov/earthquakes/eventpage/ci40659402"
    },
    {
      "id": "nc75403812",
      "lon": -122.71216583252,
      "lat": 38.7620010375977,
      "depth": 1.23000001907349,
      "mag": 1.06,
      "place": "2 km SW of Anderson Springs, CA",
      "time": 1784743361780,
      "url": "https://earthquake.usgs.gov/earthquakes/eventpage/nc75403812"
    },
    {
      "id": "ci40659410",
      "lon": -117.8715,
      "lat": 36.0966666666667,
      "depth": 3.41,
      "mag": 0.67,
      "place": "9 km NE of Coso Junction, CA",
      "time": 1784743332140,
      "url": "https://earthquake.usgs.gov/earthquakes/eventpage/ci40659410"
    },
    {
      "id": "nn00922187",
      "lon": -116.4583,
      "lat": 38.5158,
      "depth": 5.0238,
      "mag": 1.8,
      "place": "83 km NE of Tonopah, Nevada",
      "time": 1784743130591,
      "url": "https://earthquake.usgs.gov/earthquakes/eventpage/nn00922187"
    },
    {
      "id": "nc75403797",
      "lon": -122.79467010498,
      "lat": 38.8233337402344,
      "depth": 3.09999990463257,
      "mag": 0.75,
      "place": "6 km NNW of The Geysers, CA",
      "time": 1784742804330,
      "url": "https://earthquake.usgs.gov/earthquakes/eventpage/nc75403797"
    },
    {
      "id": "us7000t2h9",
      "lon": -68.5273,
      "lat": -23.3767,
      "depth": 108.731,
      "mag": 5.1,
      "place": "61 km SSW of San Pedro de Atacama, Chile",
      "time": 1784741676746,
      "url": "https://earthquake.usgs.gov/earthquakes/eventpage/us7000t2h9"
    },
    {
      "id": "aka2026oklmhc",
      "lon": -153.104,
      "lat": 60.054,
      "depth": 130.3,
      "mag": 1.9,
      "place": "63 km ENE of Pedro Bay, Alaska",
      "time": 1784741474174,
      "url": "https://earthquake.usgs.gov/earthquakes/eventpage/aka2026oklmhc"
    },
    {
      "id": "nm60625571",
      "lon": -89.5393295288086,
      "lat": 36.3993339538574,
      "depth": 8.5600004196167,
      "mag": 1.62,
      "place": "6 km WNW of Tiptonville, Tennessee",
      "time": 1784741315590,
      "url": "https://earthquake.usgs.gov/earthquakes/eventpage/nm60625571"
    },
    {
      "id": "nn00922179",
      "lon": -119.0437,
      "lat": 39.0966,
      "depth": 14,
      "mag": 3.5,
      "place": "16 km NE of Yerington, Nevada",
      "time": 1784740852315,
      "url": "https://earthquake.usgs.gov/earthquakes/eventpage/nn00922179"
    },
    {
      "id": "us7000t2h5",
      "lon": -149.6493,
      "lat": 56.1244,
      "depth": 10,
      "mag": 3.3,
      "place": "230 km SE of Chiniak, Alaska",
      "time": 1784740529796,
      "url": "https://earthquake.usgs.gov/earthquakes/eventpage/us7000t2h5"
    },
    {
      "id": "uw714057292",
      "lon": -122.678666666667,
      "lat": 47.9916666666667,
      "depth": 26.65,
      "mag": 0.98,
      "place": "6 km S of Marrowstone, Washington",
      "time": 1784740442620,
      "url": "https://earthquake.usgs.gov/earthquakes/eventpage/uw714057292"
    },
    {
      "id": "us7000t2h4",
      "lon": -92.7555,
      "lat": 14.2118,
      "depth": 35,
      "mag": 4.3,
      "place": "66 km SSW of Puerto Madero, Mexico",
      "time": 1784739810001,
      "url": "https://earthquake.usgs.gov/earthquakes/eventpage/us7000t2h4"
    },
    {
      "id": "uu80146011",
      "lon": -112.264666666667,
      "lat": 38.1713333333333,
      "depth": 1.84,
      "mag": 1.4,
      "place": "0 km E of Circleville, Utah",
      "time": 1784739582220,
      "url": "https://earthquake.usgs.gov/earthquakes/eventpage/uu80146011"
    },
    {
      "id": "ci40659378",
      "lon": -118.7255,
      "lat": 34.0095,
      "depth": 14.67,
      "mag": 0.89,
      "place": "4 km SW of Malibu Beach, CA",
      "time": 1784738855800,
      "url": "https://earthquake.usgs.gov/earthquakes/eventpage/ci40659378"
    },
    {
      "id": "aka2026okjmjg",
      "lon": -153.57,
      "lat": 60.6,
      "depth": 14.6,
      "mag": 1.3,
      "place": "60 km NE of Port Alsworth, Alaska",
      "time": 1784737880822,
      "url": "https://earthquake.usgs.gov/earthquakes/eventpage/aka2026okjmjg"
    },
    {
      "id": "tx2026oibfvf",
      "lon": -103.232,
      "lat": 31.994,
      "depth": 5.9204,
      "mag": 1.4,
      "place": "13 km SSW of Jal, New Mexico",
      "time": 1784737313128,
      "url": "https://earthquake.usgs.gov/earthquakes/eventpage/tx2026oibfvf"
    },
    {
      "id": "ci40659354",
      "lon": -116.028,
      "lat": 33.1818333333333,
      "depth": 5.41,
      "mag": 0.6,
      "place": "11 km ENE of Ocotillo Wells, CA",
      "time": 1784736053510,
      "url": "https://earthquake.usgs.gov/earthquakes/eventpage/ci40659354"
    },
    {
      "id": "ci10246238",
      "lon": -116.374333333333,
      "lat": 33.3495,
      "depth": 12.26,
      "mag": 0.8,
      "place": "10 km N of Borrego Springs, CA",
      "time": 1784735781650,
      "url": "https://earthquake.usgs.gov/earthquakes/eventpage/ci10246238"
    },
    {
      "id": "ci40659346",
      "lon": -116.390333333333,
      "lat": 33.3443333333333,
      "depth": 12.52,
      "mag": 0.86,
      "place": "10 km N of Borrego Springs, CA",
      "time": 1784735779700,
      "url": "https://earthquake.usgs.gov/earthquakes/eventpage/ci40659346"
    },
    {
      "id": "hv75006427",
      "lon": -155.158493041992,
      "lat": 19.337833404541,
      "depth": 3.46000003814697,
      "mag": 1.77,
      "place": "14 km SE of Volcano, Hawaii",
      "time": 1784735591240,
      "url": "https://earthquake.usgs.gov/earthquakes/eventpage/hv75006427"
    },
    {
      "id": "hv75006422",
      "lon": -155.151,
      "lat": 19.3328333333333,
      "depth": 7,
      "mag": 1.36,
      "place": "14 km S of Fern Forest, Hawaii",
      "time": 1784735316660,
      "url": "https://earthquake.usgs.gov/earthquakes/eventpage/hv75006422"
    },
    {
      "id": "us7000t2gx",
      "lon": -176.9767,
      "lat": -29.6426,
      "depth": 35,
      "mag": 4.8,
      "place": "Kermadec Islands region",
      "time": 1784735147284,
      "url": "https://earthquake.usgs.gov/earthquakes/eventpage/us7000t2gx"
    },
    {
      "id": "nn00922176",
      "lon": -119.0682,
      "lat": 39.3109,
      "depth": 6.5491,
      "mag": 1.83,
      "place": "17 km SE of Silver Springs, Nevada",
      "time": 1784735108094,
      "url": "https://earthquake.usgs.gov/earthquakes/eventpage/nn00922176"
    },
    {
      "id": "ci40659330",
      "lon": -117.712166666667,
      "lat": 33.511,
      "depth": 13.96,
      "mag": 1.25,
      "place": "1 km SSW of Laguna Niguel, CA",
      "time": 1784734965570,
      "url": "https://earthquake.usgs.gov/earthquakes/eventpage/ci40659330"
    },
    {
      "id": "us7000t2gq",
      "lon": -177.3364,
      "lat": -29.7099,
      "depth": 35,
      "mag": 4.9,
      "place": "Kermadec Islands, New Zealand",
      "time": 1784734762525,
      "url": "https://earthquake.usgs.gov/earthquakes/eventpage/us7000t2gq"
    },
    {
      "id": "tx2026ohyhik",
      "lon": -103.887,
      "lat": 31.954,
      "depth": 7.1509,
      "mag": 1.3,
      "place": "34 km SSE of Malaga, New Mexico",
      "time": 1784731981391,
      "url": "https://earthquake.usgs.gov/earthquakes/eventpage/tx2026ohyhik"
    },
    {
      "id": "aka2026okgdvx",
      "lon": -151.406,
      "lat": 61.252,
      "depth": 78.3,
      "mag": 1.1,
      "place": "21 km NW of Beluga, Alaska",
      "time": 1784731894053,
      "url": "https://earthquake.usgs.gov/earthquakes/eventpage/aka2026okgdvx"
    },
    {
      "id": "us7000t2gh",
      "lon": 138.8297,
      "lat": -2.5597,
      "depth": 10,
      "mag": 4.9,
      "place": "200 km W of Abepura, Indonesia",
      "time": 1784731842472,
      "url": "https://earthquake.usgs.gov/earthquakes/eventpage/us7000t2gh"
    },
    {
      "id": "pr71525308",
      "lon": -66.9131666666667,
      "lat": 17.9711666666667,
      "depth": 12.33,
      "mag": 2.42,
      "place": "0 km W of Guánica, Puerto Rico",
      "time": 1784730665450,
      "url": "https://earthquake.usgs.gov/earthquakes/eventpage/pr71525308"
    },
    {
      "id": "uu80146006",
      "lon": -110.773666666667,
      "lat": 44.7358333333333,
      "depth": 5.06,
      "mag": 1.32,
      "place": "27 km SSW of Mammoth, Wyoming",
      "time": 1784729701190,
      "url": "https://earthquake.usgs.gov/earthquakes/eventpage/uu80146006"
    },
    {
      "id": "nc75403732",
      "lon": -118.772331237793,
      "lat": 37.4246673583984,
      "depth": 1.46000003814697,
      "mag": 1.48,
      "place": "15 km W of Round Valley, CA",
      "time": 1784729687150,
      "url": "https://earthquake.usgs.gov/earthquakes/eventpage/nc75403732"
    },
    {
      "id": "hv75006372",
      "lon": -155.4475,
      "lat": 19.1181666666667,
      "depth": 27.98,
      "mag": 1.58,
      "place": "9 km SSE of Pāhala, Hawaii",
      "time": 1784727491840,
      "url": "https://earthquake.usgs.gov/earthquakes/eventpage/hv75006372"
    },
    {
      "id": "nc75403717",
      "lon": -122.809669494629,
      "lat": 38.8191680908203,
      "depth": 2.42000007629395,
      "mag": 1.89,
      "place": "7 km NW of The Geysers, CA",
      "time": 1784726589960,
      "url": "https://earthquake.usgs.gov/earthquakes/eventpage/nc75403717"
    },
    {
      "id": "ci40659266",
      "lon": -116.9765,
      "lat": 33.9963333333333,
      "depth": 11.56,
      "mag": 0.87,
      "place": "7 km E of Calimesa, CA",
      "time": 1784725739970,
      "url": "https://earthquake.usgs.gov/earthquakes/eventpage/ci40659266"
    },
    {
      "id": "ci40659258",
      "lon": -116.741,
      "lat": 33.4308333333333,
      "depth": 12.86,
      "mag": 0.83,
      "place": "12 km E of Aguanga, CA",
      "time": 1784724297810,
      "url": "https://earthquake.usgs.gov/earthquakes/eventpage/ci40659258"
    },
    {
      "id": "uu80146001",
      "lon": -111.387166666667,
      "lat": 42.36,
      "depth": 6.31,
      "mag": 1.88,
      "place": "6 km WSW of Bennington, Idaho",
      "time": 1784723956770,
      "url": "https://earthquake.usgs.gov/earthquakes/eventpage/uu80146001"
    },
    {
      "id": "uu80145991",
      "lon": -110.808,
      "lat": 44.7318333333333,
      "depth": 4.87,
      "mag": 1.63,
      "place": "24 km ENE of West Yellowstone, Montana",
      "time": 1784723553120,
      "url": "https://earthquake.usgs.gov/earthquakes/eventpage/uu80145991"
    },
    {
      "id": "ci40659242",
      "lon": -116.599,
      "lat": 33.1106666666667,
      "depth": 11.79,
      "mag": 0.61,
      "place": "4 km N of Julian, CA",
      "time": 1784723277260,
      "url": "https://earthquake.usgs.gov/earthquakes/eventpage/ci40659242"
    },
    {
      "id": "uu80145986",
      "lon": -112.292666666667,
      "lat": 38.1641666666667,
      "depth": 1.84,
      "mag": 1.31,
      "place": "2 km WSW of Circleville, Utah",
      "time": 1784722942860,
      "url": "https://earthquake.usgs.gov/earthquakes/eventpage/uu80145986"
    },
    {
      "id": "uu80145981",
      "lon": -112.314833333333,
      "lat": 38.1508333333333,
      "depth": 1.83,
      "mag": 0.94,
      "place": "4 km WSW of Circleville, Utah",
      "time": 1784722633770,
      "url": "https://earthquake.usgs.gov/earthquakes/eventpage/uu80145981"
    },
    {
      "id": "nm60625551",
      "lon": -89.6543333333333,
      "lat": 36.5436666666667,
      "depth": 8.25,
      "mag": 1.47,
      "place": "4 km NW of Marston, Missouri",
      "time": 1784721449810,
      "url": "https://earthquake.usgs.gov/earthquakes/eventpage/nm60625551"
    },
    {
      "id": "uw714057042",
      "lon": -122.214833333333,
      "lat": 46.3035,
      "depth": 4.79,
      "mag": -0.05,
      "place": "28 km S of Morton, Washington",
      "time": 1784720624260,
      "url": "https://earthquake.usgs.gov/earthquakes/eventpage/uw714057042"
    },
    {
      "id": "av94325253",
      "lon": -152.152333333333,
      "lat": 61.2915,
      "depth": -2.46,
      "mag": 0.89,
      "place": "59 km WNW of Beluga, Alaska",
      "time": 1784720442000,
      "url": "https://earthquake.usgs.gov/earthquakes/eventpage/av94325253"
    },
    {
      "id": "nn00922174",
      "lon": -116.3588,
      "lat": 38.554,
      "depth": 9.7285,
      "mag": 1.64,
      "place": "93 km NE of Tonopah, Nevada",
      "time": 1784720424034,
      "url": "https://earthquake.usgs.gov/earthquakes/eventpage/nn00922174"
    },
    {
      "id": "uw714057022",
      "lon": -121.782,
      "lat": 46.8425,
      "depth": -2.61,
      "mag": 0.68,
      "place": "21 km ENE of Ashford, Washington",
      "time": 1784720272050,
      "url": "https://earthquake.usgs.gov/earthquakes/eventpage/uw714057022"
    },
    {
      "id": "us7000t2g0",
      "lon": -68.3218,
      "lat": -23.8369,
      "depth": 126.094,
      "mag": 4.6,
      "place": "103 km S of San Pedro de Atacama, Chile",
      "time": 1784720237816,
      "url": "https://earthquake.usgs.gov/earthquakes/eventpage/us7000t2g0"
    },
    {
      "id": "uu80007688",
      "lon": -112.417,
      "lat": 41.5935,
      "depth": 2.71,
      "mag": 0.41,
      "place": "15 km SW of Thatcher, Utah",
      "time": 1784719517780,
      "url": "https://earthquake.usgs.gov/earthquakes/eventpage/uu80007688"
    },
    {
      "id": "ci40659234",
      "lon": -117.5055,
      "lat": 35.6973333333333,
      "depth": 6.98,
      "mag": 1.12,
      "place": "12 km SW of Searles Valley, CA",
      "time": 1784718960870,
      "url": "https://earthquake.usgs.gov/earthquakes/eventpage/ci40659234"
    },
    {
      "id": "ci40659226",
      "lon": -116.026,
      "lat": 33.1781666666667,
      "depth": 5.43,
      "mag": 1.15,
      "place": "11 km ENE of Ocotillo Wells, CA",
      "time": 1784718873220,
      "url": "https://earthquake.usgs.gov/earthquakes/eventpage/ci40659226"
    },
    {
      "id": "us7000t2fy",
      "lon": 141.6529,
      "lat": 37.2022,
      "depth": 47.601,
      "mag": 4.4,
      "place": "58 km ESE of Tomioka, Japan",
      "time": 1784718692578,
      "url": "https://earthquake.usgs.gov/earthquakes/eventpage/us7000t2fy"
    },
    {
      "id": "nc75403682",
      "lon": -122.931335449219,
      "lat": 38.757999420166,
      "depth": 5.63000011444092,
      "mag": 1.67,
      "place": "9 km SE of Cloverdale, CA",
      "time": 1784718606760,
      "url": "https://earthquake.usgs.gov/earthquakes/eventpage/nc75403682"
    },
    {
      "id": "ci40659218",
      "lon": -117.803833333333,
      "lat": 35.304,
      "depth": 8.13,
      "mag": 1.05,
      "place": "17 km WSW of Johannesburg, CA",
      "time": 1784718600300,
      "url": "https://earthquake.usgs.gov/earthquakes/eventpage/ci40659218"
    },
    {
      "id": "aka2026ojysvm",
      "lon": -152.846,
      "lat": 60.115,
      "depth": 121.5,
      "mag": 2.3,
      "place": "64 km WNW of Happy Valley, Alaska",
      "time": 1784718539072,
      "url": "https://earthquake.usgs.gov/earthquakes/eventpage/aka2026ojysvm"
    },
    {
      "id": "us7000t2fu",
      "lon": 147.3646,
      "lat": -5.912,
      "depth": 106.527,
      "mag": 4.7,
      "place": "89 km NW of Finschhafen, Papua New Guinea",
      "time": 1784717912056,
      "url": "https://earthquake.usgs.gov/earthquakes/eventpage/us7000t2fu"
    },
    {
      "id": "uu80145976",
      "lon": -112.281333333333,
      "lat": 38.1606666666667,
      "depth": 1.84,
      "mag": 1.37,
      "place": "1 km SW of Circleville, Utah",
      "time": 1784717597580,
      "url": "https://earthquake.usgs.gov/earthquakes/eventpage/uu80145976"
    },
    {
      "id": "pr71525293",
      "lon": -67.137,
      "lat": 17.6138333333333,
      "depth": 7.78,
      "mag": 3.03,
      "place": "40 km S of Pole Ojea, Puerto Rico",
      "time": 1784717522410,
      "url": "https://earthquake.usgs.gov/earthquakes/eventpage/pr71525293"
    },
    {
      "id": "uu80007698",
      "lon": -112.623166666667,
      "lat": 38.2596666666667,
      "depth": 5.89,
      "mag": 0.56,
      "place": "2 km SE of Beaver, Utah",
      "time": 1784717314170,
      "url": "https://earthquake.usgs.gov/earthquakes/eventpage/uu80007698"
    },
    {
      "id": "nc75403662",
      "lon": -123.421997070312,
      "lat": 39.6158332824707,
      "depth": 6.80000019073486,
      "mag": 2.07,
      "place": "10 km SSE of Laytonville, CA",
      "time": 1784716645010,
      "url": "https://earthquake.usgs.gov/earthquakes/eventpage/nc75403662"
    },
    {
      "id": "tx2026ohprvu",
      "lon": -101.056,
      "lat": 32.576,
      "depth": 3.0734,
      "mag": 1.1,
      "place": "20 km SW of Snyder, Texas",
      "time": 1784716421143,
      "url": "https://earthquake.usgs.gov/earthquakes/eventpage/tx2026ohprvu"
    },
    {
      "id": "us7000t2fq",
      "lon": -92.9016,
      "lat": 14.3451,
      "depth": 35,
      "mag": 4.5,
      "place": "66 km SW of Puerto Madero, Mexico",
      "time": 1784715893831,
      "url": "https://earthquake.usgs.gov/earthquakes/eventpage/us7000t2fq"
    },
    {
      "id": "nc75403652",
      "lon": -121.619499206543,
      "lat": 36.875,
      "depth": 6.1100001335144,
      "mag": 1.99,
      "place": "3 km SE of Aromas, CA",
      "time": 1784715837950,
      "url": "https://earthquake.usgs.gov/earthquakes/eventpage/nc75403652"
    },
    {
      "id": "uu80145971",
      "lon": -112.312166666667,
      "lat": 38.1491666666667,
      "depth": 5.9,
      "mag": 0.88,
      "place": "4 km SW of Circleville, Utah",
      "time": 1784715469670,
      "url": "https://earthquake.usgs.gov/earthquakes/eventpage/uu80145971"
    },
    {
      "id": "tx2026ohozdu",
      "lon": -104.222,
      "lat": 31.655,
      "depth": 6.8817,
      "mag": 2.3,
      "place": "55 km NW of Toyah, Texas",
      "time": 1784715151242,
      "url": "https://earthquake.usgs.gov/earthquakes/eventpage/tx2026ohozdu"
    },
    {
      "id": "us7000t2fk",
      "lon": -92.7778,
      "lat": 14.1936,
      "depth": 35,
      "mag": 4.2,
      "place": "69 km SSW of Puerto Madero, Mexico",
      "time": 1784713985939,
      "url": "https://earthquake.usgs.gov/earthquakes/eventpage/us7000t2fk"
    },
    {
      "id": "tx2026ohoilm",
      "lon": -98.963,
      "lat": 28.846,
      "depth": 7.5582,
      "mag": 2.1,
      "place": "13 km ESE of Pearsall, Texas",
      "time": 1784713953823,
      "url": "https://earthquake.usgs.gov/earthquakes/eventpage/tx2026ohoilm"
    },
    {
      "id": "hv75006322",
      "lon": -155.494833333333,
      "lat": 19.1985,
      "depth": 31.79,
      "mag": 1.76,
      "place": "1 km WSW of Pāhala, Hawaii",
      "time": 1784713723460,
      "url": "https://earthquake.usgs.gov/earthquakes/eventpage/hv75006322"
    },
    {
      "id": "nn00922171",
      "lon": -116.4978,
      "lat": 38.4568,
      "depth": 0.0117,
      "mag": 1.89,
      "place": "77 km NE of Tonopah, Nevada",
      "time": 1784713687275,
      "url": "https://earthquake.usgs.gov/earthquakes/eventpage/nn00922171"
    },
    {
      "id": "us7000t2fj",
      "lon": 125.3902,
      "lat": 5.733,
      "depth": 64.477,
      "mag": 4.9,
      "place": "11 km NW of Sugal, Philippines",
      "time": 1784713640059,
      "url": "https://earthquake.usgs.gov/earthquakes/eventpage/us7000t2fj"
    },
    {
      "id": "us7000t2fd",
      "lon": -71.7009,
      "lat": -27.8666,
      "depth": 10,
      "mag": 5.1,
      "place": "121 km NW of Vallenar, Chile",
      "time": 1784712862317,
      "url": "https://earthquake.usgs.gov/earthquakes/eventpage/us7000t2fd"
    },
    {
      "id": "ci40659210",
      "lon": -116.511833333333,
      "lat": 33.5055,
      "depth": 13.87,
      "mag": 2.2,
      "place": "16 km ESE of Anza, CA",
      "time": 1784712856540,
      "url": "https://earthquake.usgs.gov/earthquakes/eventpage/ci40659210"
    },
    {
      "id": "ci40659202",
      "lon": -117.528666666667,
      "lat": 35.6973333333333,
      "depth": 7.51,
      "mag": 0.78,
      "place": "14 km SW of Searles Valley, CA",
      "time": 1784711744400,
      "url": "https://earthquake.usgs.gov/earthquakes/eventpage/ci40659202"
    },
    {
      "id": "uw714056992",
      "lon": -122.5995,
      "lat": 48.2921666666667,
      "depth": 25.58,
      "mag": 2.1,
      "place": "3 km E of Oak Harbor, Washington",
      "time": 1784711632650,
      "url": "https://earthquake.usgs.gov/earthquakes/eventpage/uw714056992"
    },
    {
      "id": "ci40659194",
      "lon": -116.569166666667,
      "lat": 33.501,
      "depth": 11.98,
      "mag": 0.38,
      "place": "11 km ESE of Anza, CA",
      "time": 1784711607390,
      "url": "https://earthquake.usgs.gov/earthquakes/eventpage/ci40659194"
    },
    {
      "id": "tx2026ohmvlr",
      "lon": -101.686,
      "lat": 31.724,
      "depth": 7.3975,
      "mag": 2.5,
      "place": "24 km SW of Garden City, Texas",
      "time": 1784711242562,
      "url": "https://earthquake.usgs.gov/earthquakes/eventpage/tx2026ohmvlr"
    },
    {
      "id": "hv75006287",
      "lon": -155.130661010742,
      "lat": 19.1959991455078,
      "depth": 40.439998626709,
      "mag": 1.77,
      "place": "29 km SSE of Volcano, Hawaii",
      "time": 1784711166660,
      "url": "https://earthquake.usgs.gov/earthquakes/eventpage/hv75006287"
    },
    {
      "id": "pr71525288",
      "lon": -66.9968333333333,
      "lat": 18.007,
      "depth": 7,
      "mag": 2.21,
      "place": "6 km NE of La Parguera, Puerto Rico",
      "time": 1784710918630,
      "url": "https://earthquake.usgs.gov/earthquakes/eventpage/pr71525288"
    },
    {
      "id": "hv75006277",
      "lon": -155.4855,
      "lat": 19.1713333333333,
      "depth": 31.44,
      "mag": 2.22,
      "place": "3 km SSW of Pāhala, Hawaii",
      "time": 1784710356320,
      "url": "https://earthquake.usgs.gov/earthquakes/eventpage/hv75006277"
    },
    {
      "id": "aka2026ojubuq",
      "lon": -154.874,
      "lat": 58.48,
      "depth": 7.3,
      "mag": 1.5,
      "place": "104 km NNW of Karluk, Alaska",
      "time": 1784710162308,
      "url": "https://earthquake.usgs.gov/earthquakes/eventpage/aka2026ojubuq"
    },
    {
      "id": "ci40659186",
      "lon": -117.818833333333,
      "lat": 35.3045,
      "depth": 8.33,
      "mag": 1.41,
      "place": "18 km WSW of Johannesburg, CA",
      "time": 1784709722570,
      "url": "https://earthquake.usgs.gov/earthquakes/eventpage/ci40659186"
    },
    {
      "id": "uu80007703",
      "lon": -111.519166666667,
      "lat": 38.8375,
      "depth": 17.63,
      "mag": 1.03,
      "place": "25 km WSW of Emery, Utah",
      "time": 1784709023780,
      "url": "https://earthquake.usgs.gov/earthquakes/eventpage/uu80007703"
    },
    {
      "id": "ci40659178",
      "lon": -117.7925,
      "lat": 35.3586666666667,
      "depth": 4.84,
      "mag": 0.92,
      "place": "14 km W of Johannesburg, CA",
      "time": 1784709018500,
      "url": "https://earthquake.usgs.gov/earthquakes/eventpage/ci40659178"
    },
    {
      "id": "aka2026ojrguu",
      "lon": -150.519,
      "lat": 61.722,
      "depth": 61.3,
      "mag": 1.8,
      "place": "19 km N of Susitna, Alaska",
      "time": 1784705111126,
      "url": "https://earthquake.usgs.gov/earthquakes/eventpage/aka2026ojrguu"
    },
    {
      "id": "hv75006242",
      "lon": -156.11833190918,
      "lat": 19.7923336029053,
      "depth": 8.78999996185303,
      "mag": 1.85,
      "place": "15 km WNW of Kalaoa, Hawaii",
      "time": 1784704847440,
      "url": "https://earthquake.usgs.gov/earthquakes/eventpage/hv75006242"
    },
    {
      "id": "nn00922161",
      "lon": -116.4955,
      "lat": 38.4488,
      "depth": 6.7345,
      "mag": 1.9,
      "place": "76 km ENE of Tonopah, Nevada",
      "time": 1784703980832,
      "url": "https://earthquake.usgs.gov/earthquakes/eventpage/nn00922161"
    },
    {
      "id": "nn00922158",
      "lon": -116.4967,
      "lat": 38.4462,
      "depth": 6.4651,
      "mag": 1.55,
      "place": "76 km ENE of Tonopah, Nevada",
      "time": 1784703218004,
      "url": "https://earthquake.usgs.gov/earthquakes/eventpage/nn00922158"
    },
    {
      "id": "us7000t2ei",
      "lon": 138.7604,
      "lat": -2.6349,
      "depth": 21.587,
      "mag": 4.9,
      "place": "208 km W of Abepura, Indonesia",
      "time": 1784702800106,
      "url": "https://earthquake.usgs.gov/earthquakes/eventpage/us7000t2ei"
    },
    {
      "id": "nc75403592",
      "lon": -123.259002685547,
      "lat": 39.3508338928223,
      "depth": 4.5,
      "mag": 2.33,
      "place": "11 km SE of Willits, CA",
      "time": 1784702591210,
      "url": "https://earthquake.usgs.gov/earthquakes/eventpage/nc75403592"
    },
    {
      "id": "uu80007708",
      "lon": -112.327166666667,
      "lat": 38.146,
      "depth": 3.58,
      "mag": 0.58,
      "place": "5 km WSW of Circleville, Utah",
      "time": 1784701652360,
      "url": "https://earthquake.usgs.gov/earthquakes/eventpage/uu80007708"
    },
    {
      "id": "tx2026ohhfix",
      "lon": -103.486,
      "lat": 31.195,
      "depth": 5.174,
      "mag": 1.6,
      "place": "19 km SSE of Lindsay, Texas",
      "time": 1784701067617,
      "url": "https://earthquake.usgs.gov/earthquakes/eventpage/tx2026ohhfix"
    },
    {
      "id": "nc75403582",
      "lon": -121.640167236328,
      "lat": 36.9845008850098,
      "depth": 3.3199999332428,
      "mag": 1.79,
      "place": "7 km WSW of Gilroy, CA",
      "time": 1784701013070,
      "url": "https://earthquake.usgs.gov/earthquakes/eventpage/nc75403582"
    },
    {
      "id": "aka2026ojoxkq",
      "lon": -151.844,
      "lat": 61.753,
      "depth": 110.4,
      "mag": 2.3,
      "place": "35 km SW of Skwentna, Alaska",
      "time": 1784700862508,
      "url": "https://earthquake.usgs.gov/earthquakes/eventpage/aka2026ojoxkq"
    },
    {
      "id": "ci40659170",
      "lon": -116.355,
      "lat": 33.3466666666667,
      "depth": 11.93,
      "mag": 2.4,
      "place": "10 km N of Borrego Springs, CA",
      "time": 1784700840600,
      "url": "https://earthquake.usgs.gov/earthquakes/eventpage/ci40659170"
    },
    {
      "id": "uu80145961",
      "lon": -111.3965,
      "lat": 42.3766666666667,
      "depth": -1.92,
      "mag": 2.99,
      "place": "6 km WSW of Bennington, Idaho",
      "time": 1784700552780,
      "url": "https://earthquake.usgs.gov/earthquakes/eventpage/uu80145961"
    },
    {
      "id": "ci40659162",
      "lon": -116.880333333333,
      "lat": 33.7978333333333,
      "depth": 13.54,
      "mag": 0.94,
      "place": "6 km NNE of Valle Vista, CA",
      "time": 1784699057600,
      "url": "https://earthquake.usgs.gov/earthquakes/eventpage/ci40659162"
    },
    {
      "id": "nc75403562",
      "lon": -121.148170471191,
      "lat": 36.5766677856445,
      "depth": 9.86999988555908,
      "mag": 1.31,
      "place": "5 km N of Pinnacles, CA",
      "time": 1784698885780,
      "url": "https://earthquake.usgs.gov/earthquakes/eventpage/nc75403562"
    },
    {
      "id": "tx2026ohfwtc",
      "lon": -104.22,
      "lat": 31.655,
      "depth": 6.4075,
      "mag": 1.5,
      "place": "55 km NW of Toyah, Texas",
      "time": 1784698669945,
      "url": "https://earthquake.usgs.gov/earthquakes/eventpage/tx2026ohfwtc"
    },
    {
      "id": "us7000t2e4",
      "lon": -126.7179,
      "lat": 43.3879,
      "depth": 10,
      "mag": 3,
      "place": "189 km W of Bandon, Oregon",
      "time": 1784696998751,
      "url": "https://earthquake.usgs.gov/earthquakes/eventpage/us7000t2e4"
    },
    {
      "id": "aka2026ojmrlb",
      "lon": -154.888,
      "lat": 57.663,
      "depth": 16.6,
      "mag": 2.1,
      "place": "27 km WNW of Karluk, Alaska",
      "time": 1784696850151,
      "url": "https://earthquake.usgs.gov/earthquakes/eventpage/aka2026ojmrlb"
    },
    {
      "id": "tx2026ohewoa",
      "lon": -103.88,
      "lat": 31.96,
      "depth": 7.843,
      "mag": 1,
      "place": "34 km SSE of Malaga, New Mexico",
      "time": 1784696842982,
      "url": "https://earthquake.usgs.gov/earthquakes/eventpage/tx2026ohewoa"
    },
    {
      "id": "tx2026oherya",
      "lon": -104.259,
      "lat": 31.805,
      "depth": 6.0614,
      "mag": 1.6,
      "place": "42 km SSE of Whites City, New Mexico",
      "time": 1784696649886,
      "url": "https://earthquake.usgs.gov/earthquakes/eventpage/tx2026oherya"
    },
    {
      "id": "hv75006167",
      "lon": -155.496673583984,
      "lat": 19.1504993438721,
      "depth": 29.2000007629395,
      "mag": 1.79,
      "place": "6 km SSW of Pāhala, Hawaii",
      "time": 1784695475430,
      "url": "https://earthquake.usgs.gov/earthquakes/eventpage/hv75006167"
    },
    {
      "id": "ci40659154",
      "lon": -116.490166666667,
      "lat": 33.508,
      "depth": 13.68,
      "mag": 0.52,
      "place": "18 km ESE of Anza, CA",
      "time": 1784695071890,
      "url": "https://earthquake.usgs.gov/earthquakes/eventpage/ci40659154"
    },
    {
      "id": "tx2026ohdhby",
      "lon": -103.464,
      "lat": 31.172,
      "depth": 3.1775,
      "mag": 1.1,
      "place": "22 km SSE of Lindsay, Texas",
      "time": 1784693948001,
      "url": "https://earthquake.usgs.gov/earthquakes/eventpage/tx2026ohdhby"
    },
    {
      "id": "us7000t2dz",
      "lon": 97.5238,
      "lat": 4.2441,
      "depth": 10,
      "mag": 5,
      "place": "55 km WSW of Langsa, Indonesia",
      "time": 1784693902071,
      "url": "https://earthquake.usgs.gov/earthquakes/eventpage/us7000t2dz"
    },
    {
      "id": "uw714056922",
      "lon": -121.1285,
      "lat": 46.7293333333333,
      "depth": 7.3,
      "mag": 1.07,
      "place": "17 km SW of Nile, Washington",
      "time": 1784693828560,
      "url": "https://earthquake.usgs.gov/earthquakes/eventpage/uw714056922"
    },
    {
      "id": "nn00922155",
      "lon": -116.7028,
      "lat": 38.3647,
      "depth": 2.6007,
      "mag": 1.82,
      "place": "56 km NE of Tonopah, Nevada",
      "time": 1784693443565,
      "url": "https://earthquake.usgs.gov/earthquakes/eventpage/nn00922155"
    },
    {
      "id": "hv75006132",
      "lon": -155.380340576172,
      "lat": 18.9545001983643,
      "depth": 16.5900001525879,
      "mag": 1.8,
      "place": "24 km ESE of Naalehu, Hawaii",
      "time": 1784693296320,
      "url": "https://earthquake.usgs.gov/earthquakes/eventpage/hv75006132"
    },
    {
      "id": "ci40659146",
      "lon": -116.028,
      "lat": 33.1796666666667,
      "depth": 5.34,
      "mag": 1.38,
      "place": "10 km ENE of Ocotillo Wells, CA",
      "time": 1784693132810,
      "url": "https://earthquake.usgs.gov/earthquakes/eventpage/ci40659146"
    },
    {
      "id": "nc75403532",
      "lon": -122.780670166016,
      "lat": 38.8084983825684,
      "depth": 2.95000004768372,
      "mag": 1.11,
      "place": "4 km NNW of The Geysers, CA",
      "time": 1784692895790,
      "url": "https://earthquake.usgs.gov/earthquakes/eventpage/nc75403532"
    },
    {
      "id": "nc75403527",
      "lon": -122.752502441406,
      "lat": 38.7936668395996,
      "depth": 1.73000001907349,
      "mag": 0.75,
      "place": "2 km N of The Geysers, CA",
      "time": 1784692787160,
      "url": "https://earthquake.usgs.gov/earthquakes/eventpage/nc75403527"
    },
    {
      "id": "ci40659138",
      "lon": -116.512666666667,
      "lat": 33.4993333333333,
      "depth": 13.32,
      "mag": 0.97,
      "place": "16 km ESE of Anza, CA",
      "time": 1784692475890,
      "url": "https://earthquake.usgs.gov/earthquakes/eventpage/ci40659138"
    },
    {
      "id": "us7000t2dw",
      "lon": -92.8732,
      "lat": 14.3993,
      "depth": 35,
      "mag": 4,
      "place": "60 km SW of Puerto Madero, Mexico",
      "time": 1784692110298,
      "url": "https://earthquake.usgs.gov/earthquakes/eventpage/us7000t2dw"
    },
    {
      "id": "us7000t2dv",
      "lon": 148.9654,
      "lat": 44.4209,
      "depth": 35,
      "mag": 4.6,
      "place": "124 km SE of Kuril’sk, Russia",
      "time": 1784691949474,
      "url": "https://earthquake.usgs.gov/earthquakes/eventpage/us7000t2dv"
    },
    {
      "id": "ci40659130",
      "lon": -117.153833333333,
      "lat": 33.9868333333333,
      "depth": 11.14,
      "mag": 0.96,
      "place": "8 km SSE of Redlands, CA",
      "time": 1784691364590,
      "url": "https://earthquake.usgs.gov/earthquakes/eventpage/ci40659130"
    },
    {
      "id": "nc75403502",
      "lon": -122.804664611816,
      "lat": 38.8253326416016,
      "depth": 2.6800000667572,
      "mag": 0.87,
      "place": "7 km NW of The Geysers, CA",
      "time": 1784691350210,
      "url": "https://earthquake.usgs.gov/earthquakes/eventpage/nc75403502"
    },
    {
      "id": "ci40659122",
      "lon": -118.972166666667,
      "lat": 34.836,
      "depth": 12.4,
      "mag": 1.28,
      "place": "3 km WNW of Frazier Park, CA",
      "time": 1784691231800,
      "url": "https://earthquake.usgs.gov/earthquakes/eventpage/ci40659122"
    },
    {
      "id": "hv75006112",
      "lon": -155.494833333333,
      "lat": 19.2026666666667,
      "depth": 30.94,
      "mag": 2.25,
      "place": "1 km W of Pāhala, Hawaii",
      "time": 1784691208410,
      "url": "https://earthquake.usgs.gov/earthquakes/eventpage/hv75006112"
    },
    {
      "id": "aka2026ojjkem",
      "lon": -159.813,
      "lat": 55.84,
      "depth": 8.7,
      "mag": 2.2,
      "place": "21 km WSW of Ivanof Bay, Alaska",
      "time": 1784690950856,
      "url": "https://earthquake.usgs.gov/earthquakes/eventpage/aka2026ojjkem"
    },
    {
      "id": "ci40659114",
      "lon": -117.815666666667,
      "lat": 35.3053333333333,
      "depth": 8.57,
      "mag": 1.22,
      "place": "18 km WSW of Johannesburg, CA",
      "time": 1784690865030,
      "url": "https://earthquake.usgs.gov/earthquakes/eventpage/ci40659114"
    },
    {
      "id": "tx2026ohbjdz",
      "lon": -103.243,
      "lat": 32.012,
      "depth": 7.074,
      "mag": 1.4,
      "place": "12 km SSW of Jal, New Mexico",
      "time": 1784690470832,
      "url": "https://earthquake.usgs.gov/earthquakes/eventpage/tx2026ohbjdz"
    },
    {
      "id": "uw714056912",
      "lon": -122.254666666667,
      "lat": 44.1768333333333,
      "depth": 5.31,
      "mag": 1.2,
      "place": "30 km SE of Cascadia, Oregon",
      "time": 1784689998440,
      "url": "https://earthquake.usgs.gov/earthquakes/eventpage/uw714056912"
    },
    {
      "id": "aka2026ojivev",
      "lon": -152.187,
      "lat": 59.832,
      "depth": 81.7,
      "mag": 1.6,
      "place": "20 km WNW of Anchor Point, Alaska",
      "time": 1784689913891,
      "url": "https://earthquake.usgs.gov/earthquakes/eventpage/aka2026ojivev"
    },
    {
      "id": "uw714056902",
      "lon": -121.922833333333,
      "lat": 46.863,
      "depth": 10.94,
      "mag": 0.25,
      "place": "14 km NE of Ashford, Washington",
      "time": 1784689877630,
      "url": "https://earthquake.usgs.gov/earthquakes/eventpage/uw714056902"
    },
    {
      "id": "uu80145956",
      "lon": -112.3025,
      "lat": 38.1731666666667,
      "depth": 5.88,
      "mag": 2.06,
      "place": "2 km W of Circleville, Utah",
      "time": 1784688927710,
      "url": "https://earthquake.usgs.gov/earthquakes/eventpage/uu80145956"
    },
    {
      "id": "aka2026ojigbg",
      "lon": -152.725,
      "lat": 60.364,
      "depth": 130,
      "mag": 2.9,
      "place": "68 km WNW of Ninilchik, Alaska",
      "time": 1784688865429,
      "url": "https://earthquake.usgs.gov/earthquakes/eventpage/aka2026ojigbg"
    },
    {
      "id": "ci40659098",
      "lon": -118.343166666667,
      "lat": 34.1058333333333,
      "depth": 18.87,
      "mag": 0.94,
      "place": "2 km WNW of Hollywood, CA",
      "time": 1784688375140,
      "url": "https://earthquake.usgs.gov/earthquakes/eventpage/ci40659098"
    },
    {
      "id": "nc75403472",
      "lon": -120.436164855957,
      "lat": 35.8821678161621,
      "depth": 10.039999961853,
      "mag": 1,
      "place": "2 km SSW of Parkfield, CA",
      "time": 1784688039250,
      "url": "https://earthquake.usgs.gov/earthquakes/eventpage/nc75403472"
    },
    {
      "id": "nn00922153",
      "lon": -116.5143,
      "lat": 38.4686,
      "depth": 11.4822,
      "mag": 1.75,
      "place": "76 km NE of Tonopah, Nevada",
      "time": 1784687677158,
      "url": "https://earthquake.usgs.gov/earthquakes/eventpage/nn00922153"
    },
    {
      "id": "nn00922149",
      "lon": -119.0651,
      "lat": 39.3144,
      "depth": 6.2471,
      "mag": 1.52,
      "place": "17 km SE of Silver Springs, Nevada",
      "time": 1784687482399,
      "url": "https://earthquake.usgs.gov/earthquakes/eventpage/nn00922149"
    },
    {
      "id": "aka2026ojhjrl",
      "lon": -141.201,
      "lat": 61.441,
      "depth": 24.9,
      "mag": 1.6,
      "place": "91 km E of McCarthy, Alaska",
      "time": 1784687317621,
      "url": "https://earthquake.usgs.gov/earthquakes/eventpage/aka2026ojhjrl"
    },
    {
      "id": "nn00922145",
      "lon": -119.0609,
      "lat": 39.3117,
      "depth": 6.4131,
      "mag": 1.66,
      "place": "18 km SE of Silver Springs, Nevada",
      "time": 1784687172893,
      "url": "https://earthquake.usgs.gov/earthquakes/eventpage/nn00922145"
    },
    {
      "id": "nn00922144",
      "lon": -119.0602,
      "lat": 39.3139,
      "depth": 6.6011,
      "mag": 1.77,
      "place": "18 km SE of Silver Springs, Nevada",
      "time": 1784687090286,
      "url": "https://earthquake.usgs.gov/earthquakes/eventpage/nn00922144"
    },
    {
      "id": "av94324663",
      "lon": -174.150666666667,
      "lat": 52.4135,
      "depth": 7.26,
      "mag": 0.99,
      "place": "24 km N of Atka, Alaska",
      "time": 1784686225170,
      "url": "https://earthquake.usgs.gov/earthquakes/eventpage/av94324663"
    },
    {
      "id": "nn00922141",
      "lon": -115.7647,
      "lat": 36.7014,
      "depth": 6.6294,
      "mag": 1.79,
      "place": "16 km NNW of Indian Springs, Nevada",
      "time": 1784686045618,
      "url": "https://earthquake.usgs.gov/earthquakes/eventpage/nn00922141"
    },
    {
      "id": "us7000t2dg",
      "lon": -70.1036,
      "lat": -19.2494,
      "depth": 60.814,
      "mag": 4.7,
      "place": "12 km SE of Cuya, Chile",
      "time": 1784685830385,
      "url": "https://earthquake.usgs.gov/earthquakes/eventpage/us7000t2dg"
    },
    {
      "id": "hv75006072",
      "lon": -155.499160766602,
      "lat": 19.191499710083,
      "depth": 28.7199993133545,
      "mag": 1.84,
      "place": "2 km WSW of Pāhala, Hawaii",
      "time": 1784685731180,
      "url": "https://earthquake.usgs.gov/earthquakes/eventpage/hv75006072"
    },
    {
      "id": "uw714056872",
      "lon": -122.559166666667,
      "lat": 47.7675,
      "depth": 26.5,
      "mag": 1.14,
      "place": "3 km NW of Indianola, Washington",
      "time": 1784685595570,
      "url": "https://earthquake.usgs.gov/earthquakes/eventpage/uw714056872"
    },
    {
      "id": "us7000t2dd",
      "lon": -70.7197,
      "lat": -23.5367,
      "depth": 35,
      "mag": 4.1,
      "place": "35 km WNW of Antofagasta, Chile",
      "time": 1784684925228,
      "url": "https://earthquake.usgs.gov/earthquakes/eventpage/us7000t2dd"
    },
    {
      "id": "nc75403452",
      "lon": -122.806831359863,
      "lat": 38.8358345031738,
      "depth": 2.20000004768372,
      "mag": 1.26,
      "place": "7 km WNW of Cobb, CA",
      "time": 1784684795060,
      "url": "https://earthquake.usgs.gov/earthquakes/eventpage/nc75403452"
    },
    {
      "id": "nc75403427",
      "lon": -122.815170288086,
      "lat": 38.8293342590332,
      "depth": 1.76999998092651,
      "mag": 0.71,
      "place": "8 km NW of The Geysers, CA",
      "time": 1784682999400,
      "url": "https://earthquake.usgs.gov/earthquakes/eventpage/nc75403427"
    },
    {
      "id": "nn00922136",
      "lon": -116.4878,
      "lat": 38.4398,
      "depth": 9.998,
      "mag": 2.3,
      "place": "77 km ENE of Tonopah, Nevada",
      "time": 1784682204349,
      "url": "https://earthquake.usgs.gov/earthquakes/eventpage/nn00922136"
    },
    {
      "id": "nc75403417",
      "lon": -121.138999938965,
      "lat": 36.5563316345215,
      "depth": 6.75,
      "mag": 1.19,
      "place": "3 km N of Pinnacles, CA",
      "time": 1784681036380,
      "url": "https://earthquake.usgs.gov/earthquakes/eventpage/nc75403417"
    },
    {
      "id": "hv75006052",
      "lon": -155.445327758789,
      "lat": 19.3066673278809,
      "depth": 46.7900009155273,
      "mag": 1.71,
      "place": "12 km NNE of Pāhala, Hawaii",
      "time": 1784680901530,
      "url": "https://earthquake.usgs.gov/earthquakes/eventpage/hv75006052"
    },
    {
      "id": "nn00922133",
      "lon": -116.5035,
      "lat": 38.4456,
      "depth": 5.8552,
      "mag": 1.82,
      "place": "76 km ENE of Tonopah, Nevada",
      "time": 1784680211474,
      "url": "https://earthquake.usgs.gov/earthquakes/eventpage/nn00922133"
    },
    {
      "id": "ci40659090",
      "lon": -116.7455,
      "lat": 33.5086666666667,
      "depth": 4.09,
      "mag": 1.79,
      "place": "8 km SW of Anza, CA",
      "time": 1784679218480,
      "url": "https://earthquake.usgs.gov/earthquakes/eventpage/ci40659090"
    },
    {
      "id": "nc75403402",
      "lon": -118.333168029785,
      "lat": 37.0876655578613,
      "depth": 1.37000000476837,
      "mag": 2.27,
      "place": "9 km SSW of Big Pine, CA",
      "time": 1784679198630,
      "url": "https://earthquake.usgs.gov/earthquakes/eventpage/nc75403402"
    },
    {
      "id": "tx2026oguydd",
      "lon": -103.246,
      "lat": 32.009,
      "depth": 6.7151,
      "mag": 2.6,
      "place": "12 km SSW of Jal, New Mexico",
      "time": 1784678853666,
      "url": "https://earthquake.usgs.gov/earthquakes/eventpage/tx2026oguydd"
    },
    {
      "id": "uu80145946",
      "lon": -112.314166666667,
      "lat": 38.1716666666667,
      "depth": 1.84,
      "mag": 1.56,
      "place": "3 km W of Circleville, Utah",
      "time": 1784678760050,
      "url": "https://earthquake.usgs.gov/earthquakes/eventpage/uu80145946"
    },
    {
      "id": "aka2026ojcptu",
      "lon": -152.824,
      "lat": 59.811,
      "depth": 109.2,
      "mag": 1.9,
      "place": "55 km W of Anchor Point, Alaska",
      "time": 1784678743874,
      "url": "https://earthquake.usgs.gov/earthquakes/eventpage/aka2026ojcptu"
    },
    {
      "id": "uw714056752",
      "lon": -122.5365,
      "lat": 47.5733333333333,
      "depth": 19.9,
      "mag": 0.6,
      "place": "2 km NNE of Manchester, Washington",
      "time": 1784678186070,
      "url": "https://earthquake.usgs.gov/earthquakes/eventpage/uw714056752"
    },
    {
      "id": "aka2026ojccrj",
      "lon": -152.915,
      "lat": 59.953,
      "depth": 118,
      "mag": 2.3,
      "place": "63 km WNW of Anchor Point, Alaska",
      "time": 1784677838836,
      "url": "https://earthquake.usgs.gov/earthquakes/eventpage/aka2026ojccrj"
    },
    {
      "id": "ci40659082",
      "lon": -116.711833333333,
      "lat": 33.5401666666667,
      "depth": 5.49,
      "mag": 0.17,
      "place": "4 km WSW of Anza, CA",
      "time": 1784677572680,
      "url": "https://earthquake.usgs.gov/earthquakes/eventpage/ci40659082"
    },
    {
      "id": "us7000t2cl",
      "lon": 69.3313,
      "lat": 35.6983,
      "depth": 121.887,
      "mag": 4.4,
      "place": "44 km SSE of Nahrīn, Afghanistan",
      "time": 1784677485433,
      "url": "https://earthquake.usgs.gov/earthquakes/eventpage/us7000t2cl"
    },
    {
      "id": "aka2026ojbxgj",
      "lon": -155.422,
      "lat": 57.37,
      "depth": 10.1,
      "mag": 1.7,
      "place": "62 km WSW of Karluk, Alaska",
      "time": 1784677464096,
      "url": "https://earthquake.usgs.gov/earthquakes/eventpage/aka2026ojbxgj"
    },
    {
      "id": "uw714056742",
      "lon": -122.212,
      "lat": 48.4386666666667,
      "depth": -0.68,
      "mag": 0.63,
      "place": "3 km SSE of Clear Lake, Washington",
      "time": 1784677084130,
      "url": "https://earthquake.usgs.gov/earthquakes/eventpage/uw714056742"
    },
    {
      "id": "ci40659074",
      "lon": -116.539833333333,
      "lat": 33.4651666666667,
      "depth": 11.06,
      "mag": 0.62,
      "place": "16 km SE of Anza, CA",
      "time": 1784676681870,
      "url": "https://earthquake.usgs.gov/earthquakes/eventpage/ci40659074"
    },
    {
      "id": "nn00922128",
      "lon": -116.4836,
      "lat": 38.4058,
      "depth": 12.4849,
      "mag": 1.55,
      "place": "75 km ENE of Tonopah, Nevada",
      "time": 1784676606497,
      "url": "https://earthquake.usgs.gov/earthquakes/eventpage/nn00922128"
    },
    {
      "id": "pr71525278",
      "lon": -64.7525,
      "lat": 18.1331666666667,
      "depth": 7.98,
      "mag": 2.28,
      "place": "22 km S of Cruz Bay, U.S. Virgin Islands",
      "time": 1784676378610,
      "url": "https://earthquake.usgs.gov/earthquakes/eventpage/pr71525278"
    },
    {
      "id": "ci40659066",
      "lon": -116.768166666667,
      "lat": 33.5043333333333,
      "depth": 4.81,
      "mag": 0.82,
      "place": "10 km WSW of Anza, CA",
      "time": 1784675576590,
      "url": "https://earthquake.usgs.gov/earthquakes/eventpage/ci40659066"
    },
    {
      "id": "aka2026ojaozy",
      "lon": -155.55,
      "lat": 57.021,
      "depth": 5,
      "mag": 1.9,
      "place": "84 km W of Akhiok, Alaska",
      "time": 1784675092248,
      "url": "https://earthquake.usgs.gov/earthquakes/eventpage/aka2026ojaozy"
    },
    {
      "id": "tx2026ogsvzm",
      "lon": -101.921,
      "lat": 32.093,
      "depth": 5.4199,
      "mag": 0.4,
      "place": "13 km WSW of Stanton, Texas",
      "time": 1784675072534,
      "url": "https://earthquake.usgs.gov/earthquakes/eventpage/tx2026ogsvzm"
    },
    {
      "id": "uw714056672",
      "lon": -120.471666666667,
      "lat": 49.3166666666667,
      "depth": -0.62,
      "mag": 2.23,
      "place": "15 km S of Princeton, Canada",
      "time": 1784674951770,
      "url": "https://earthquake.usgs.gov/earthquakes/eventpage/uw714056672"
    },
    {
      "id": "nc75403347",
      "lon": -122.484169006348,
      "lat": 37.6064987182617,
      "depth": 10.6700000762939,
      "mag": 1.48,
      "place": "1 km SSE of Pacifica, CA",
      "time": 1784674935500,
      "url": "https://earthquake.usgs.gov/earthquakes/eventpage/nc75403347"
    },
    {
      "id": "ok2026oezr",
      "lon": -97.18083333,
      "lat": 34.07283333,
      "depth": 0,
      "mag": 1.34,
      "place": "11 km SSW of Ardmore, Oklahoma",
      "time": 1784674881820,
      "url": "https://earthquake.usgs.gov/earthquakes/eventpage/ok2026oezr"
    },
    {
      "id": "nc75403342",
      "lon": -122.737663269043,
      "lat": 38.8030014038086,
      "depth": 0.779999971389771,
      "mag": 0.59,
      "place": "2 km SSW of Cobb, CA",
      "time": 1784674698060,
      "url": "https://earthquake.usgs.gov/earthquakes/eventpage/nc75403342"
    },
    {
      "id": "tx2026ogshof",
      "lon": -104.444,
      "lat": 31.656,
      "depth": 6.0999,
      "mag": 1.8,
      "place": "57 km S of Whites City, New Mexico",
      "time": 1784674066030,
      "url": "https://earthquake.usgs.gov/earthquakes/eventpage/tx2026ogshof"
    },
    {
      "id": "aka2026oizpwh",
      "lon": -155.452,
      "lat": 57.423,
      "depth": 12.2,
      "mag": 2.9,
      "place": "61 km WSW of Karluk, Alaska",
      "time": 1784673353247,
      "url": "https://earthquake.usgs.gov/earthquakes/eventpage/aka2026oizpwh"
    },
    {
      "id": "uw714056602",
      "lon": -123.6,
      "lat": 49.0761666666667,
      "depth": 14.62,
      "mag": 1.42,
      "place": "17 km E of North Oyster/Yellow Point, Canada",
      "time": 1784673299190,
      "url": "https://earthquake.usgs.gov/earthquakes/eventpage/uw714056602"
    },
    {
      "id": "uu80145941",
      "lon": -112.923,
      "lat": 37.023,
      "depth": 16.57,
      "mag": 0.97,
      "place": "4 km ENE of Hildale, Utah",
      "time": 1784673288320,
      "url": "https://earthquake.usgs.gov/earthquakes/eventpage/uu80145941"
    },
    {
      "id": "us7000t2c9",
      "lon": 168.6204,
      "lat": -17.9675,
      "depth": 146.721,
      "mag": 4.8,
      "place": "41 km SE of Port-Vila, Vanuatu",
      "time": 1784673181323,
      "url": "https://earthquake.usgs.gov/earthquakes/eventpage/us7000t2c9"
    },
    {
      "id": "hv75005962",
      "lon": -155.494833333333,
      "lat": 19.1986666666667,
      "depth": 30.8,
      "mag": 2.24,
      "place": "1 km WSW of Pāhala, Hawaii",
      "time": 1784672896630,
      "url": "https://earthquake.usgs.gov/earthquakes/eventpage/hv75005962"
    },
    {
      "id": "tx2026ogrpui",
      "lon": -101.738,
      "lat": 31.702,
      "depth": 7.4951,
      "mag": 0.6,
      "place": "30 km SW of Garden City, Texas",
      "time": 1784672849256,
      "url": "https://earthquake.usgs.gov/earthquakes/eventpage/tx2026ogrpui"
    },
    {
      "id": "uu80145936",
      "lon": -112.277666666667,
      "lat": 38.1636666666667,
      "depth": 1.55,
      "mag": 1.48,
      "place": "1 km SW of Circleville, Utah",
      "time": 1784671662910,
      "url": "https://earthquake.usgs.gov/earthquakes/eventpage/uu80145936"
    },
    {
      "id": "aka2026oiyepg",
      "lon": -154.964,
      "lat": 58.283,
      "depth": 5,
      "mag": 1.4,
      "place": "85 km NNW of Karluk, Alaska",
      "time": 1784670773451,
      "url": "https://earthquake.usgs.gov/earthquakes/eventpage/aka2026oiyepg"
    },
    {
      "id": "nn00922119",
      "lon": -116.4972,
      "lat": 38.4538,
      "depth": 9.8099,
      "mag": 2.16,
      "place": "77 km ENE of Tonopah, Nevada",
      "time": 1784670489116,
      "url": "https://earthquake.usgs.gov/earthquakes/eventpage/nn00922119"
    },
    {
      "id": "uw714056522",
      "lon": -122.499333333333,
      "lat": 46.4415,
      "depth": 18.61,
      "mag": 1.67,
      "place": "9 km S of Mossyrock, Washington",
      "time": 1784670441550,
      "url": "https://earthquake.usgs.gov/earthquakes/eventpage/uw714056522"
    },
    {
      "id": "nn00922117",
      "lon": -116.4909,
      "lat": 38.4443,
      "depth": 10.9173,
      "mag": 1.65,
      "place": "77 km ENE of Tonopah, Nevada",
      "time": 1784670396433,
      "url": "https://earthquake.usgs.gov/earthquakes/eventpage/nn00922117"
    },
    {
      "id": "uw714056482",
      "lon": -120.560333333333,
      "lat": 46.2261666666667,
      "depth": 8.35,
      "mag": 0.73,
      "place": "19 km S of Harrah, Washington",
      "time": 1784668930550,
      "url": "https://earthquake.usgs.gov/earthquakes/eventpage/uw714056482"
    },
    {
      "id": "nc75403317",
      "lon": -122.782669067383,
      "lat": 38.8409996032715,
      "depth": 7.82999992370605,
      "mag": 0.28,
      "place": "6 km WNW of Cobb, CA",
      "time": 1784668800750,
      "url": "https://earthquake.usgs.gov/earthquakes/eventpage/nc75403317"
    },
    {
      "id": "uu80145921",
      "lon": -112.310333333333,
      "lat": 38.17,
      "depth": 0.56,
      "mag": 2.14,
      "place": "3 km W of Circleville, Utah",
      "time": 1784668647920,
      "url": "https://earthquake.usgs.gov/earthquakes/eventpage/uu80145921"
    },
    {
      "id": "uw714056462",
      "lon": -120.5595,
      "lat": 46.2266666666667,
      "depth": 11.49,
      "mag": 0.86,
      "place": "19 km S of Harrah, Washington",
      "time": 1784668293330,
      "url": "https://earthquake.usgs.gov/earthquakes/eventpage/uw714056462"
    },
    {
      "id": "uu80145916",
      "lon": -112.288166666667,
      "lat": 38.1693333333333,
      "depth": 2.07,
      "mag": 1.54,
      "place": "1 km W of Circleville, Utah",
      "time": 1784668237640,
      "url": "https://earthquake.usgs.gov/earthquakes/eventpage/uu80145916"
    },
    {
      "id": "tx2026ogoqup",
      "lon": -102.059,
      "lat": 32.357,
      "depth": 7.1533,
      "mag": 0.6,
      "place": "35 km NW of Stanton, Texas",
      "time": 1784667473426,
      "url": "https://earthquake.usgs.gov/earthquakes/eventpage/tx2026ogoqup"
    },
    {
      "id": "tx2026ogoizr",
      "lon": -104.375,
      "lat": 31.654,
      "depth": 6.0999,
      "mag": 1.7,
      "place": "57 km S of Whites City, New Mexico",
      "time": 1784667137134,
      "url": "https://earthquake.usgs.gov/earthquakes/eventpage/tx2026ogoizr"
    },
    {
      "id": "nn00922112",
      "lon": -116.4714,
      "lat": 38.4981,
      "depth": 2.5234,
      "mag": 2,
      "place": "81 km NE of Tonopah, Nevada",
      "time": 1784666155062,
      "url": "https://earthquake.usgs.gov/earthquakes/eventpage/nn00922112"
    }
  ]
}